{
	"info": {
		"_postman_id": "6c02d1c6-bd75-452f-9402-89fc8d261fac",
		"name": "Jira",
		"schema": "https://schema.getpostman.com/json/collection/v2.1.0/collection.json"
	},
	"item": [
		{
			"name": "createmeta",
			"event": [
				{
					"listen": "test",
					"script": {
						"exec": [
							"pm.test(\"Status is 200\", function () {",
							"    pm.response.to.have.status(200);",
							"});",
							"",
							"pm.test(\"SetCollectionVariables\", function () {",
							"    var jsonData = pm.response.json();",
							"    pm.collectionVariables.set(\"project_key\", jsonData.projects[1].key);",
							"    pm.collectionVariables.set(\"issue_typeId\", jsonData.projects[1].issuetypes[4].id);",
							"});"
						],
						"type": "text/javascript"
					}
				}
			],
			"request": {
				"method": "GET",
				"header": [],
				"url": {
					"raw": "http://89.223.126.182:8080/rest/api/2/issue/createmeta",
					"protocol": "http",
					"host": [
						"89",
						"223",
						"126",
						"182"
					],
					"port": "8080",
					"path": [
						"rest",
						"api",
						"2",
						"issue",
						"createmeta"
					]
				}
			},
			"response": []
		},
		{
			"name": "issue",
			"event": [
				{
					"listen": "test",
					"script": {
						"exec": [
							"pm.test(\"Status code is 201\", function () {",
							"    pm.response.to.have.status(201);",
							"});",
							"",
							"pm.test(\"SetCollectionVariables\", function () {",
							"    var jsonData = pm.response.json();",
							"    pm.collectionVariables.set(\"issue_Id\", jsonData.id);",
							"});"
						],
						"type": "text/javascript"
					}
				},
				{
					"listen": "prerequest",
					"script": {
						"exec": [
							"var rnd = Math.random();",
							"",
							"pm.collectionVariables.set(\"summary\", \"Erokhova_AT_\" + rnd);",
							"pm.collectionVariables.set(\"description\", \"Description_AT_\" + rnd);",
							""
						],
						"type": "text/javascript"
					}
				}
			],
			"request": {
				"method": "POST",
				"header": [],
				"body": {
					"mode": "raw",
					"raw": "{\n    \"fields\": {\n        \"project\": {\n            \"key\": \"{{project_key}}\"\n        },\n        \"summary\": \"{{summary}}\",\n        \"description\": \"{{description}}\",\n        \"issuetype\": {\n            \"id\": \"{{issue_typeId}}\"\n        }\n    }\n}",
					"options": {
						"raw": {
							"language": "json"
						}
					}
				},
				"url": {
					"raw": "http://89.223.126.182:8080/rest/api/2/issue",
					"protocol": "http",
					"host": [
						"89",
						"223",
						"126",
						"182"
					],
					"port": "8080",
					"path": [
						"rest",
						"api",
						"2",
						"issue"
					]
				}
			},
			"response": []
		},
		{
			"name": "issue",
			"event": [
				{
					"listen": "test",
					"script": {
						"exec": [
							"pm.test(\"Status code is 200\", function () {",
							"    pm.response.to.have.status(200);",
							"});",
							"",
							"pm.test(\"summary and description test\", function () {",
							"    var jsonData = pm.response.json();",
							"",
							"    pm.expect(jsonData.fields.summary).to.eql(pm.collectionVariables.get(\"summary\"));",
							"    pm.expect(jsonData.fields.description).to.eql(pm.collectionVariables.get(\"description\"));",
							"});"
						],
						"type": "text/javascript"
					}
				}
			],
			"request": {
				"method": "GET",
				"header": [],
				"url": {
					"raw": "http://89.223.126.182:8080/rest/api/2/issue/{{issue_Id}}",
					"protocol": "http",
					"host": [
						"89",
						"223",
						"126",
						"182"
					],
					"port": "8080",
					"path": [
						"rest",
						"api",
						"2",
						"issue",
						"{{issue_Id}}"
					]
				}
			},
			"response": []
		},
		{
			"name": "transitions",
			"event": [
				{
					"listen": "test",
					"script": {
						"exec": [
							"pm.test(\"Status code is 200\", function () {",
							"    pm.response.to.have.status(200);",
							"});",
							"pm.test(\"SetCollectionVariables\", function () {",
							"    var jsonData = pm.response.json();",
							"    pm.collectionVariables.set(\"transition_ID\", jsonData.transitions[1].id);",
							"    pm.collectionVariables.set(\"transition\", jsonData.transitions[1].to.id);",
							"});"
						],
						"type": "text/javascript"
					}
				}
			],
			"request": {
				"method": "GET",
				"header": [],
				"url": {
					"raw": "http://89.223.126.182:8080/rest/api/2/issue/{{issue_Id}}/transitions",
					"protocol": "http",
					"host": [
						"89",
						"223",
						"126",
						"182"
					],
					"port": "8080",
					"path": [
						"rest",
						"api",
						"2",
						"issue",
						"{{issue_Id}}",
						"transitions"
					]
				}
			},
			"response": []
		},
		{
			"name": "transitions",
			"event": [
				{
					"listen": "test",
					"script": {
						"exec": [
							"pm.test(\"Status code is 204\", function () {",
							"    pm.response.to.have.status(204);",
							"});"
						],
						"type": "text/javascript"
					}
				}
			],
			"request": {
				"method": "POST",
				"header": [],
				"body": {
					"mode": "raw",
					"raw": "{\n\t\"transition\": {\n      \"id\": {{transition_ID}}\n    }\n}\n",
					"options": {
						"raw": {
							"language": "json"
						}
					}
				},
				"url": {
					"raw": "http://89.223.126.182:8080/rest/api/2/issue/{{issue_Id}}/transitions",
					"protocol": "http",
					"host": [
						"89",
						"223",
						"126",
						"182"
					],
					"port": "8080",
					"path": [
						"rest",
						"api",
						"2",
						"issue",
						"{{issue_Id}}",
						"transitions"
					]
				}
			},
			"response": []
		},
		{
			"name": "issue Copy",
			"event": [
				{
					"listen": "test",
					"script": {
						"exec": [
							"pm.test(\"Status code is 200\", function () {",
							"    pm.response.to.have.status(200);",
							"});",
							"",
							"pm.test(\"status check\", function () {",
							"    var jsonData = pm.response.json();",
							"    pm.expect(jsonData.fields.status.id).to.eql(pm.collectionVariables.get(\"transition\"));",
							"});"
						],
						"type": "text/javascript"
					}
				}
			],
			"request": {
				"method": "GET",
				"header": [],
				"url": {
					"raw": "http://89.223.126.182:8080/rest/api/2/issue/{{issue_Id}}",
					"protocol": "http",
					"host": [
						"89",
						"223",
						"126",
						"182"
					],
					"port": "8080",
					"path": [
						"rest",
						"api",
						"2",
						"issue",
						"{{issue_Id}}"
					]
				}
			},
			"response": []
		}
	],
	"auth": {
		"type": "basic",
		"basic": [
			{
				"key": "password",
				"value": "123456",
				"type": "string"
			},
			{
				"key": "username",
				"value": "v.volochaeva@bk.ru",
				"type": "string"
			}
		]
	},
	"event": [
		{
			"listen": "prerequest",
			"script": {
				"type": "text/javascript",
				"exec": [
					""
				]
			}
		},
		{
			"listen": "test",
			"script": {
				"type": "text/javascript",
				"exec": [
					""
				]
			}
		}
	],
	"variable": [
		{
			"key": "project_key",
			"value": ""
		},
		{
			"key": "issue_typeID",
			"value": ""
		},
		{
			"key": "issue_typeId",
			"value": ""
		},
		{
			"key": "summary",
			"value": ""
		},
		{
			"key": "description",
			"value": ""
		},
		{
			"key": "issue_Id",
			"value": ""
		},
		{
			"key": "transition_ID",
			"value": ""
		},
		{
			"key": "transition",
			"value": ""
		}
	]
}